MANIFEST.in
README.txt
setup.py
docs/HISTORY.txt
docs/LICENSE.txt
src/silva/__init__.py
src/silva.app.shorturl.egg-info/PKG-INFO
src/silva.app.shorturl.egg-info/SOURCES.txt
src/silva.app.shorturl.egg-info/dependency_links.txt
src/silva.app.shorturl.egg-info/namespace_packages.txt
src/silva.app.shorturl.egg-info/not-zip-safe
src/silva.app.shorturl.egg-info/requires.txt
src/silva.app.shorturl.egg-info/top_level.txt
src/silva/app/__init__.py
src/silva/app/shorturl/__init__.py
src/silva/app/shorturl/codec.py
src/silva/app/shorturl/configure.zcml
src/silva/app/shorturl/ftesting.zcml
src/silva/app/shorturl/interfaces.py
src/silva/app/shorturl/service.py
src/silva/app/shorturl/smi.py
src/silva/app/shorturl/testing.py
src/silva/app/shorturl/traverse.py
src/silva/app/shorturl/smi_templates/custompathwidget.cpt
src/silva/app/shorturl/smi_templates/displayshorturlwidget.cpt
src/silva/app/shorturl/smi_templates/shorturlinformation.cpt
src/silva/app/shorturl/static/custom_path.css
src/silva/app/shorturl/static/custom_path.js
src/silva/app/shorturl/static/display_shorturl.js
src/silva/app/shorturl/static/service_shorturls.png
src/silva/app/shorturl/tests/__init__.py
src/silva/app/shorturl/tests/test_service.py
src/silva/app/shorturl/tests/test_traversing.py