Metadata-Version: 1.1
Name: silva.app.shorturl
Version: 3.0.2
Summary: Short url generation for Silva CMS
Home-page: https://github.com/silvacms/silva.app.shorturl
Author: Infrae
Author-email: info@infrae.com
License: BSD
Keywords: silva shorturl
Platform: UNKNOWN
Classifier: Framework :: Zope2
Classifier: License :: OSI Approved :: BSD License
Classifier: Programming Language :: Python
Classifier: Topic :: Software Development :: Libraries :: Python Modules
